{
	"configurations" : 
	[
		{
			"directories" : 
			[
				{
					"build" : ".",
					"minimumCMakeVersion" : 
					{
						"string" : "3.10"
					},
					"projectIndex" : 0,
					"source" : ".",
					"targetIndexes" : 
					[
						0,
						1
					]
				}
			],
			"name" : "Debug",
			"projects" : 
			[
				{
					"directoryIndexes" : 
					[
						0
					],
					"name" : "simple_redis",
					"targetIndexes" : 
					[
						0,
						1
					]
				}
			],
			"targets" : 
			[
				{
					"directoryIndex" : 0,
					"id" : "simple_redis::@6890427a1f51a3e7e1df",
					"jsonFile" : "target-simple_redis-Debug-17f6cb204e0db9e7193c.json",
					"name" : "simple_redis",
					"projectIndex" : 0
				},
				{
					"directoryIndex" : 0,
					"id" : "simple_redis_optimized::@6890427a1f51a3e7e1df",
					"jsonFile" : "target-simple_redis_optimized-Debug-04542af760c93a6b7f78.json",
					"name" : "simple_redis_optimized",
					"projectIndex" : 0
				}
			]
		}
	],
	"kind" : "codemodel",
	"paths" : 
	{
		"build" : "/root/C++_Projects/simple_redis/build",
		"source" : "/root/C++_Projects/simple_redis"
	},
	"version" : 
	{
		"major" : 2,
		"minor" : 0
	}
}
